neurommsig_knowledge/Acetylcholine signaling subgraph.bel
neurommsig_knowledge/Acetylcholine signaling subgraph.bel.json
neurommsig_knowledge/Amyloidogenic subgraph.bel
neurommsig_knowledge/Amyloidogenic subgraph.bel.json
neurommsig_knowledge/Apoptosis signaling subgraph.bel
neurommsig_knowledge/Apoptosis signaling subgraph.bel.json
neurommsig_knowledge/DKK1 subgraph.bel
neurommsig_knowledge/DKK1 subgraph.bel.json
neurommsig_knowledge/Free radical formation subgraph.bel
neurommsig_knowledge/Free radical formation subgraph.bel.json
neurommsig_knowledge/GABA subgraph.bel
neurommsig_knowledge/GABA subgraph.bel.json
neurommsig_knowledge/GSK3 subgraph.bel
neurommsig_knowledge/GSK3 subgraph.bel.json
neurommsig_knowledge/Hydrogen peroxide subgraph.bel
neurommsig_knowledge/Hydrogen peroxide subgraph.bel.json
neurommsig_knowledge/Inflammatory response subgraph.bel
neurommsig_knowledge/Inflammatory response subgraph.bel.json
neurommsig_knowledge/Insulin signal transduction.bel
neurommsig_knowledge/Insulin signal transduction.bel.json
neurommsig_knowledge/Low density lipoprotein subgraph.bel
neurommsig_knowledge/Low density lipoprotein subgraph.bel.json
neurommsig_knowledge/Myeloperoxidase subgraph.bel
neurommsig_knowledge/Myeloperoxidase subgraph.bel.json
neurommsig_knowledge/Neurotransmitter release subgraph.bel
neurommsig_knowledge/Neurotransmitter release subgraph.bel.json
neurommsig_knowledge/Nitric oxide subgraph.bel
neurommsig_knowledge/Nitric oxide subgraph.bel.json
neurommsig_knowledge/Non-amyloidogenic subgraph.bel
neurommsig_knowledge/Non-amyloidogenic subgraph.bel.json
neurommsig_knowledge/Notch signaling subgraph.bel
neurommsig_knowledge/Notch signaling subgraph.bel.json
neurommsig_knowledge/Reactive oxygen species subgraph.bel
neurommsig_knowledge/Reactive oxygen species subgraph.bel.json
neurommsig_knowledge/Tau protein subgraph.bel
neurommsig_knowledge/Tau protein subgraph.bel.json
neurommsig_knowledge/__init__.py
neurommsig_knowledge/__main__.py
neurommsig_knowledge-0.0.1.dist-info/LICENSE
neurommsig_knowledge-0.0.1.dist-info/METADATA
neurommsig_knowledge-0.0.1.dist-info/WHEEL
neurommsig_knowledge-0.0.1.dist-info/entry_points.txt
neurommsig_knowledge-0.0.1.dist-info/top_level.txt
neurommsig_knowledge-0.0.1.dist-info/RECORD
